[
  {
    "id": "5510c566-588c-43f4-8aa7-0aec9b481700",
    "group": "FOOTER_NAV",
    "labelZh": "测试导航2",
    "labelEn": "Test Nav 2",
    "href": "/test",
    "order": 1,
    "createdAt": "2026-03-01T21:49:04.503Z",
    "updatedAt": "2026-03-01T21:50:48.057Z"
  },
  {
    "id": "550799dc-0c7c-4427-ae72-1aa2e9ed7859",
    "group": "HEADER_MAIN",
    "labelZh": "我的首饰",
    "labelEn": "My Jewelry",
    "href": "/collections?category=jewelry",
    "order": 1,
    "createdAt": "2026-03-01T21:47:47.028Z",
    "updatedAt": "2026-03-01T21:50:35.512Z"
  },
  {
    "id": "6b513cce-d997-418c-93db-0c5f4c4f7826",
    "group": "HEADER_MEGA_CATEGORY",
    "labelZh": "Somdej (DB) ZH",
    "labelEn": "Somdej (DB)",
    "href": "/collections?category=somdej",
    "order": 1,
    "createdAt": "2026-03-14T13:41:31.203Z",
    "updatedAt": "2026-03-14T13:42:08.856Z"
  }
]